Metadata-Version: 1.2
Name: pywebvis
Version: 0.0.1
Summary: A live two-way data binder for python
Home-page: https://github.com/DaniloZZZ/pywebvis
Author: Danil Lykov
Author-email: lkvdan@gmail.com
License: MIT
Keywords: tools,data,framework,visualization
Platform: UNKNOWN
Requires-Python: >=3.3
